order_journey/__init__.py
order_journey/visualizer.py
order_journey_viz-0.2.0.dist-info/licenses/LICENSE
order_journey_viz-0.2.0.dist-info/METADATA
order_journey_viz-0.2.0.dist-info/WHEEL
order_journey_viz-0.2.0.dist-info/top_level.txt
order_journey_viz-0.2.0.dist-info/RECORD
