Metadata-Version: 2.4
Name: order-journey-viz
Version: 0.2.0
Summary: Interactive visualization of order status journeys
Author-email: Aditya Shah <adityarobots21@gmail.com>
License-Expression: MIT
Project-URL: Homepage, https://github.com/venom21adi/order-journey-viz
Requires-Python: >=3.8
License-File: LICENSE
Requires-Dist: pandas
Dynamic: license-file
